pyextractme/__init__.py
pyextractme/__main__.py
pyextractme/main.py
pyextractme-0.1.0.dist-info/METADATA
pyextractme-0.1.0.dist-info/WHEEL
pyextractme-0.1.0.dist-info/entry_points.txt
pyextractme-0.1.0.dist-info/top_level.txt
pyextractme-0.1.0.dist-info/RECORD
