Metadata-Version: 2.4
Name: pyextractme
Version: 0.1.0
Summary: extract files from the compressed file (.zip/.tar.gz/.gz)
Project-URL: Homepage, https://github.com/fxyzbtc/pyextractme
Project-URL: Issues, https://github.com/fxyzbtc/pyextractme/issues
Requires-Python: >=3.12
Requires-Dist: pytest>=8.3.5
Requires-Dist: loguru>=0.7.3
Requires-Dist: typer>=0.15.2
Provides-Extra: dev
Requires-Dist: pytest>=8.3.5; extra == "dev"
Requires-Dist: pytest-cov>=4.1.0; extra == "dev"
Requires-Dist: black>=24.2.0; extra == "dev"
Requires-Dist: isort>=5.13.2; extra == "dev"
